[1,["263gFXhepAc67GkK1wQ1bB@f9941","18Vlx/NoRBvbt8UByhmGRO@6c48a","69AigoB3BCha6Chje6wDw5@6c48a","56o1xOGK1HlYat8Ruz66pa@f9941","bfdJsy0XdFOYVywUIwrFr/@f9941","18Vlx/NoRBvbt8UByhmGRO@f9941","69AigoB3BCha6Chje6wDw5@f9941","adB/K37wdELrqxW/sEwVHk@f9941","81lj/r9SxJHLyCwbpCVTwn@f9941","bfdJsy0XdFOYVywUIwrFr/@6c48a"],["node","_spriteFrame","_textureSource","root","content","scrollView","closeBtn","panel","black","data","_parent"],[["cc.Node",["_name","_layer","_components","_prefab","_parent","_children","_lpos","_lscale"],1,9,4,1,2,5,5],["cc.Sprite",["_sizeMode","_type","_useGrayscale","node","__prefab","_spriteFrame","_color"],0,1,4,6,5],"cc.SpriteFrame",["cc.UITransform",["node","__prefab","_contentSize","_anchorPoint"],3,1,4,5,5],["cc.Node",["_name","_layer","_parent","_components","_prefab","_lpos","_children"],1,1,12,4,5,2],["cc.Widget",["_alignFlags","_originalWidth","_originalHeight","_top","_bottom","node","__prefab"],-2,1,4],["cc.Prefab",["_name"],2],["cc.CompPrefabInfo",["fileId"],2],["cc.BlockInputEvents",["node","__prefab"],3,1,4],["71686309ABLYrlbWjmfq0Oh",["node","__prefab","black","panel","closeBtn","scrollView","content"],3,1,4,1,1,1,1,1],["cc.PrefabInfo",["fileId","instance","targetOverrides","nestedPrefabInstanceRoots","root","asset"],-1,1,1],["cc.UIOpacity",["node","__prefab"],3,1,4],["cc.Mask",["node","__prefab"],3,1,4],["cc.Graphics",["node","__prefab","_fillColor"],3,1,4,5],["cc.Button",["_transition","_zoomScale","node","__prefab","_normalColor","_target"],1,1,4,5,1],["cc.ScrollView",["bounceDuration","brake","horizontal","node","__prefab","_content"],0,1,4,1]],[[7,0,2],[10,0,1,2,3,4,5,5],[3,0,1,2,1],[0,0,1,4,2,3,3],[0,0,1,4,5,2,3,6,3],[1,3,4,5,1],[0,0,1,4,5,2,3,6,7,3],[3,0,1,1],[3,0,1,2,3,1],[1,0,3,4,5,2],[6,0,2],[0,0,1,5,2,3,3],[0,0,1,5,2,3,7,3],[0,0,1,4,5,2,3,3],[0,0,1,4,2,3,6,3],[0,0,1,4,2,3,6,7,3],[4,0,1,2,3,4,5,3],[4,0,1,2,6,3,4,5,3],[5,0,1,2,5,6,4],[5,0,3,4,1,2,5,6,6],[8,0,1,1],[9,0,1,2,3,4,5,6,1],[1,0,3,4,6,5,2],[1,1,0,3,4,5,3],[1,1,0,3,4,3],[1,0,2,3,4,5,3],[1,3,4,1],[11,0,1,1],[12,0,1,1],[13,0,1,2,1],[14,0,1,2,3,4,5,3],[15,0,1,2,3,4,5,4]],[[[{"name":"场景","rect":{"x":0,"y":0,"width":114,"height":61},"offset":{"x":0,"y":0},"originalSize":{"width":114,"height":61},"rotated":false,"capInsets":[0,0,0,0],"vertices":{"rawPosition":[-57,-30.5,0,57,-30.5,0,-57,30.5,0,57,30.5,0],"indexes":[0,1,2,2,1,3],"uv":[0,61,114,61,0,0,114,0],"nuv":[0,0,1,0,0,1,1,1],"minPos":{"x":-57,"y":-30.5,"z":0},"maxPos":{"x":57,"y":30.5,"z":0}},"packable":true,"pixelsToUnit":100,"pivot":{"x":0.5,"y":0.5},"meshType":0}],[2],0,[0],[2],[1]],[[{"name":"鸽鸽图鉴","rect":{"x":0,"y":0,"width":493,"height":160},"offset":{"x":0,"y":0},"originalSize":{"width":493,"height":160},"rotated":false,"capInsets":[0,0,0,0],"vertices":{"rawPosition":[-246.5,-80,0,246.5,-80,0,-246.5,80,0,246.5,80,0],"indexes":[0,1,2,2,1,3],"uv":[0,160,493,160,0,0,493,0],"nuv":[0,0,1,0,0,1,1,1],"minPos":{"x":-246.5,"y":-80,"z":0},"maxPos":{"x":246.5,"y":80,"z":0}},"packable":true,"pixelsToUnit":100,"pivot":{"x":0.5,"y":0.5},"meshType":0}],[2],0,[0],[2],[2]],[[[10,"BookPigeonUI"],[11,"BookPigeonUI",33554432,[-11,-12],[[2,-2,[0,"f9bXmWB01A2p52d4ZgSRs6"],[5,1080,1920]],[18,45,40,36,-3,[0,"2fxhoC13FGuaHInbtnniTX"]],[20,-4,[0,"50pibDPjpMj6mWi9WPReO3"]],[21,-10,[0,"f5G8VoO3ZG5ZYyclSa+/S+"],-9,-8,-7,-6,-5]],[1,"6e/Og4AjtME62g6o2lyBkP",null,null,null,-1,0]],[3,"black",33554432,1,[[2,-13,[0,"9e4GVxNctMlKdG7hd3eFoZ"],[5,1080,1960]],[22,0,-14,[0,"20eCvUCPRCAr7hY9sMFrc0"],[4,4278190080],0],[19,45,-20,-20,40,36,-15,[0,"61zlFvWXBH2LihDVbatzQ2"]],[27,-16,[0,"75mi+5f5lNGLAeggs/nRU+"]]],[1,"5cNShIohJAArruswwH+CVA",null,null,null,1,0]],[12,"baseMap",33554432,[-19,-20,-21],[[2,-17,[0,"2ejXVgdx5HIYAPPNIoreTb"],[5,839,1163]],[9,0,-18,[0,"cebPzY5+JHh5DS43/Q+s8R"],7]],[1,"2bQmq4Y95ELK7K/V6Nu2u2",null,null,null,1,0],[1,1.2,1.2,1]],[13,"panel",33554432,1,[-23,3],[[2,-22,[0,"47RGhS+hNKM7gDxTxfHhOp"],[5,0,0]]],[1,"80zYmk5GlDcrbbnEw3bjHT",null,null,null,1,0]],[16,"closeBtn",33554432,3,[[[7,-24,[0,"e1ccfQ2c1N4KWz73CnYwZi"]],[23,1,0,-25,[0,"c6GSlxUMlIcK/Uk3btTyxX"],6],-26],4,4,1],[1,"02uBP/e8xM7ZhXdfblYUpk",null,null,null,1,0],[1,406.558,555,0]],[17,"ScrollView",33554432,3,[-30],[[[2,-27,[0,"d7hw/FaVhHoovwbx0H41gc"],[5,660,850]],[24,1,0,-28,[0,"2ayFJsJ3lMorIp0j9AESFm"]],-29],4,4,1],[1,"abISdjXBdMwJuYc6V9lUX1",null,null,null,1,0],[1,0,38.549,0]],[4,"view",33554432,6,[-34],[[8,-31,[0,"1axmqsXF9KgJi9/9bq/XHL"],[5,800,950],[0,0.5,1]],[28,-32,[0,"55MHAmECNPQK/+yEX1buCp"]],[29,-33,[0,"a0vv3ce2NFLYTKBHo/P40a"],[4,16777215]]],[1,"e1nYrNq8JD5oQcGl6Rz1tG",null,null,null,1,0],[1,0,425,0]],[6,"chooseBtn",33554432,4,[-36,-37],[[7,-35,[0,"b1h+BgIfZFpbxVrJ9YQU7t"]]],[1,"9dOoV3AyNGbaBW2NrxR8m3",null,null,null,1,0],[1,0,-701.751,0],[1,1.2,1.2,1]],[4,"角色",33554432,8,[-40],[[2,-38,[0,"d8z4YiUyNBAatA+kF3FWcf"],[5,187.52,99.84]],[9,0,-39,[0,"6a0moE2/tJkqO/+pOpUeK4"],2]],[1,"32WCjgCCxP0qpyHxag0yBY",null,null,null,1,0],[1,-277.203,-15,0]],[4,"场景",33554432,8,[-43],[[2,-41,[0,"d2Jj9aWWtGv7ISxY7hDB/M"],[5,187.52,99.84]],[25,0,true,-42,[0,"f4kje3YKRCGq0VwdH7Tgmo"],4]],[1,"d5LWFI6AxMJbEtakCVq5kH",null,null,null,1,0],[1,-83.473,0,0]],[6,"title",33554432,3,[-46],[[2,-44,[0,"36eTRuvs1EuqmatLUxlXec"],[5,493,160]],[5,-45,[0,"33hAA24ulPVbURmGn8FNVn"],5]],[1,"cb57CF549KDqUl6KOblu0c",null,null,null,1,0],[1,0,566,0],[1,0.8,0.8,1]],[14,"content",33554432,7,[[8,-47,[0,"08xV4rztRO3oRE19GPi2l5"],[5,800,15400],[0,0.5,1]]],[1,"8f2xWN00VJg7gUTvGrji/T",null,null,null,1,0],[1,0,427.453,0]],[3,"角色",33554432,9,[[2,-48,[0,"51fKKd98lHi4957L1s7cME"],[5,114,62]],[5,-49,[0,"efqGC5HD1KtYXhUQqy+y1f"],1]],[1,"fdMRGm5gBBman3qdGMy87k",null,null,null,1,0]],[15,"场景",33554432,10,[[2,-50,[0,"32+iv4+GVFfbimVTOUyBCD"],[5,114,61]],[5,-51,[0,"7aSoVwKfpIoJXk/jmLXL+I"],3]],[1,"35UR9riYJEvYKoEjJfAvNy",null,null,null,1,0],[1,0,-15,0],[1,0.8,0.8,1]],[3,"word",33554432,11,[[2,-52,[0,"a5VyaSx6dM05o1XVYS6z4F"],[5,137,73]],[26,-53,[0,"28lIaoiCZPTKDHTcOonN2+"]]],[1,"aavDqOGPdJx4ht5E18jJYZ",null,null,null,1,0]],[30,3,1.1,5,[0,"7eTUiACExAoaMfA+f1lnS5"],[4,4292269782],5],[31,0.23,0.75,false,6,[0,"9fOWem1nFHvoMBSjKqKW0X"],12]],0,[0,3,1,0,0,1,0,0,1,0,0,1,0,4,12,0,5,17,0,6,16,0,7,4,0,8,2,0,0,1,0,-1,2,0,-2,4,0,0,2,0,0,2,0,0,2,0,0,2,0,0,3,0,0,3,0,-1,11,0,-2,5,0,-3,6,0,0,4,0,-1,8,0,0,5,0,0,5,0,-3,16,0,0,6,0,0,6,0,-3,17,0,-1,7,0,0,7,0,0,7,0,0,7,0,-1,12,0,0,8,0,-1,9,0,-2,10,0,0,9,0,0,9,0,-1,13,0,0,10,0,0,10,0,-1,14,0,0,11,0,0,11,0,-1,15,0,0,12,0,0,13,0,0,13,0,0,14,0,0,14,0,0,15,0,0,15,0,9,1,3,10,4,53],[0,0,0,0,0,0,0,0],[1,1,1,1,1,1,1,1],[3,4,0,5,0,6,7,8]],[[{"name":"角色","rect":{"x":0,"y":0,"width":114,"height":62},"offset":{"x":0,"y":0},"originalSize":{"width":114,"height":62},"rotated":false,"capInsets":[0,0,0,0],"vertices":{"rawPosition":[-57,-31,0,57,-31,0,-57,31,0,57,31,0],"indexes":[0,1,2,2,1,3],"uv":[0,62,114,62,0,0,114,0],"nuv":[0,0,1,0,0,1,1,1],"minPos":{"x":-57,"y":-31,"z":0},"maxPos":{"x":57,"y":31,"z":0}},"packable":true,"pixelsToUnit":100,"pivot":{"x":0.5,"y":0.5},"meshType":0}],[2],0,[0],[2],[9]]]]
